imasensurvey/__init__.py
imasensurvey/imasen.py
imasensurvey-1.0.5.dist-info/LICENSE
imasensurvey-1.0.5.dist-info/METADATA
imasensurvey-1.0.5.dist-info/WHEEL
imasensurvey-1.0.5.dist-info/top_level.txt
imasensurvey-1.0.5.dist-info/RECORD
