Metadata-Version: 2.1
Name: imasensurvey
Version: 1.0.5
Summary: Descarga de audios SurveyToGo
Home-page: UNKNOWN
Author: Matias Canales
Author-email: <matias.canales@alum.udep.edu.pe>
License: UNKNOWN
Keywords: python,imasen
Platform: UNKNOWN
Classifier: Development Status :: 1 - Planning
Classifier: Intended Audience :: Developers
Classifier: Programming Language :: Python :: 3
Classifier: Operating System :: Unix
Classifier: Operating System :: MacOS :: MacOS X
Classifier: Operating System :: Microsoft :: Windows
Requires-Dist: pandas
Requires-Dist: pathlib
Requires-Dist: pytest-shutil
